graphomaly/__init__.py
graphomaly/estimator.py
graphomaly/grid_search.py
graphomaly/normalizations.py
graphomaly/voting.py
graphomaly/models/__init__.py
graphomaly/models/autoencoder.py
graphomaly/models/base_model.py
graphomaly/models/dictlearn.py
graphomaly/models/models.py
graphomaly/models/sklearn.py
graphomaly/models/vae.py
graphomaly/preprocessing/__init__.py
graphomaly/preprocessing/egonet.py
graphomaly/preprocessing/fe_difference_transformer.py
graphomaly/preprocessing/fe_statistical_transformer.py
graphomaly/preprocessing/fe_time_transformers.py
graphomaly/preprocessing/graph_to_features.py
graphomaly/preprocessing/graph_to_spectrum_features.py
graphomaly/preprocessing/rwalk.py
graphomaly/preprocessing/spectrum.py
graphomaly/preprocessing/transactions_to_graph.py
graphomaly/preprocessing/fe_base/__init__.py
graphomaly/preprocessing/fe_base/historical_features.py
graphomaly/preprocessing/fe_base/statistical_features.py
graphomaly/preprocessing/fe_base/time_features.py
graphomaly-0.3.2.dist-info/licenses/LICENSE
graphomaly-0.3.2.dist-info/METADATA
graphomaly-0.3.2.dist-info/WHEEL
graphomaly-0.3.2.dist-info/top_level.txt
graphomaly-0.3.2.dist-info/RECORD
