Metadata-Version: 2.4
Name: graphomaly
Version: 0.3.2
Summary: Anomaly detection in graphs modeling financial transactions and computer networks.
Home-page: https://gitlab.com/unibuc/graphomaly/graphomaly
Author: Paul Irofti, Ștefania Budulan, Bogdan Dumitrescu, Andra Băltoiu, Nicolae Cleju, Andrei Iulian Hîji
Author-email: graphomaly@fmi.unibuc.ro
Project-URL: Bug Tracker, https://gitlab.com/unibuc/graphomaly/graphomaly/-/issues
Keywords: anomaly detection,graphs,financial transactions,computer networks,abnormal behavior,machine learning,security
Classifier: Programming Language :: Python :: 3
Classifier: License :: OSI Approved :: BSD License
Classifier: Operating System :: OS Independent
Requires-Python: >=3.6
License-File: LICENSE
Requires-Dist: attrdict3
Requires-Dist: combo
Requires-Dist: dirty-cat
Requires-Dist: dictlearn
Requires-Dist: keras
Requires-Dist: networkx<3
Requires-Dist: numpy>=1.19
Requires-Dist: pandas
Requires-Dist: tqdm
Requires-Dist: pyod>=1.1.0
Requires-Dist: python-louvain
Requires-Dist: PyYAML
Requires-Dist: scikit-learn>1.1.3
Requires-Dist: scipy
Requires-Dist: tensorflow
Requires-Dist: wheel
Requires-Dist: wrapt-timeout-decorator
Dynamic: license-file
